Metadata-Version: 1.1
Name: linselect
Version: 0.1.1
Summary: A fast, flexible, and performant feature selection package for python.
Home-page: https://github.com/EFavDB/linselect
Author: Jonathan Landy
Author-email: jslandy@gmail.com
License: MIT
Download-URL: https://github.com/efavdb/linselect/archive/0.1.1.tar.gz
Platform: UNKNOWN
